native_mcp/__init__.py
native_mcp/imsdk/__init__.py
native_mcp/imsdk/engine.py
native_mcp/imsdk/util.py
native_mcp/lib/librust_universal_imsdk.dylib
native_mcp/lib/rcim_client.h
native_mcp/lib/rcim_client.py
native_mcp/lib/rcim_utils.py
native_mcp/lib/rust_db/RongCloud/global.kv
native_mcp/lib/rust_db/RongCloud/c9kqb3rdkbb8j/rc-log.db
native_mcp/lib/rust_db/RongCloud/c9kqb3rdkbb8j/rc-log.db-shm
native_mcp/lib/rust_db/RongCloud/c9kqb3rdkbb8j/rc-log.db-wal
native_mcp/lib/rust_db/RongCloud/c9kqb3rdkbb8j/5PmaSCHfI/resend_msg.kv
native_mcp/lib/rust_db/RongCloud/c9kqb3rdkbb8j/5PmaSCHfI/storage
native_mcp/lib/rust_db/RongCloud/c9kqb3rdkbb8j/5PmaSCHfI/storage-shm
native_mcp/lib/rust_db/RongCloud/c9kqb3rdkbb8j/5PmaSCHfI/storage-wal
native_mcp/lib/rust_db/RongCloud/c9kqb3rdkbb8j/5PmaSCHfI/user.kv
native_mcp/server/__init__.py
native_mcp/server/server.py
native_mcp/utils/__init__.py
native_mcp/utils/mcp_utils.py
rc_im_native_mcp_server-0.1.10.dist-info/METADATA
rc_im_native_mcp_server-0.1.10.dist-info/WHEEL
rc_im_native_mcp_server-0.1.10.dist-info/entry_points.txt
rc_im_native_mcp_server-0.1.10.dist-info/RECORD
