Metadata-Version: 2.4
Name: rc-im-native-mcp-server
Version: 0.1.10
Summary: Rongcloud IM Service based on MCP Protocol (Rust SDK Wrapper)
Project-URL: Homepage, https://github.com/rongcloud/RC-IM-Native-MCP-Server
Project-URL: Repository, https://github.com/rongcloud/RC-IM-Native-MCP-Server.git
Author-email: Rongcloud <imsdk@rongcloud.cn>
Requires-Python: >=3.10
Requires-Dist: click>=8.0.0
Requires-Dist: mcp[cli]
Requires-Dist: pydantic
Requires-Dist: pydantic-settings
Requires-Dist: uvicorn
Provides-Extra: dev
Requires-Dist: pip-tools; extra == 'dev'
